some_crap/__init__.py
some_crap/version.py
some_crap-0.0.3.dist-info/METADATA
some_crap-0.0.3.dist-info/WHEEL
some_crap-0.0.3.dist-info/top_level.txt
some_crap-0.0.3.dist-info/RECORD
