Metadata-Version: 2.1
Name: some-crap
Version: 0.0.3
Summary: Python client for evidently nothing
Author: Some Random guy
Author-email: some-random-guy@gmail.com
License: MIT
Keywords: nothing crap
Classifier: Development Status :: 2 - Pre-Alpha
Classifier: Intended Audience :: Developers
Classifier: License :: OSI Approved :: MIT License
Classifier: Natural Language :: English
Classifier: Programming Language :: Python :: 3.6
Classifier: Programming Language :: Python :: 3.7
Classifier: Programming Language :: Python :: 3.8
Classifier: Programming Language :: Python :: 3.9
Requires-Python: >=3.6
Requires-Dist: Appium-Python-Client (==1.*)
Requires-Dist: requests (==2.*)
